config.toml.dist
time_log.py
time_log-0.1.10.dist-info/entry_points.txt
time_log-0.1.10.dist-info/LICENSE
time_log-0.1.10.dist-info/WHEEL
time_log-0.1.10.dist-info/METADATA
time_log-0.1.10.dist-info/RECORD
