Metadata-Version: 2.1
Name: time-log
Version: 0.1.10
Summary: Prototype for a time tracker/logger command line utility
Home-page: https://github.com/resingm/tl-prototype
License: GPL-3.0-only
Author: Max Resing
Author-email: max.resing@protonmail.com
Maintainer: Max Resing
Maintainer-email: max.resing@protonmail.com
Requires-Python: >=3.9,<4.0
Classifier: Development Status :: 3 - Alpha
Classifier: Environment :: Console
Classifier: Intended Audience :: End Users/Desktop
Classifier: License :: OSI Approved :: GNU General Public License v3 (GPLv3)
Classifier: Operating System :: Unix
Classifier: Programming Language :: Python
Classifier: Programming Language :: Python :: 3
Classifier: Programming Language :: Python :: 3.9
Requires-Dist: pretty-tables (>=1.3.0,<2.0.0)
Requires-Dist: yacf (>=1.1.0,<2.0.0)
Project-URL: Bug Tracker, https://github.com/resingm/tl-prototype/issues
Project-URL: Documentation, https://github.com/resingm/tl-prototype
Project-URL: Repository, https://github.com/resingm/tl-prototype
